dtjson/__init__.py
json_dt_serializer-1.1.0.dist-info/LICENSE
json_dt_serializer-1.1.0.dist-info/LICENSE.txt
json_dt_serializer-1.1.0.dist-info/METADATA
json_dt_serializer-1.1.0.dist-info/WHEEL
json_dt_serializer-1.1.0.dist-info/RECORD
