Metadata-Version: 2.1
Name: json-dt-serializer
Version: 1.1.0
Summary: JSON, but with datetime and timestamp support
License: LICENSE.txt
Author: Ken Kinder
Author-email: ken+github@kkinder.com
Requires-Python: >=3.9,<4.0
Classifier: Development Status :: 4 - Beta
Classifier: Intended Audience :: Developers
Classifier: License :: OSI Approved :: MIT License
Classifier: License :: Other/Proprietary License
Classifier: Programming Language :: Python :: 3
Classifier: Programming Language :: Python :: 3.9
Classifier: Programming Language :: Python :: 3.10
Classifier: Programming Language :: Python :: 3.11
Classifier: Topic :: File Formats :: JSON
Classifier: Topic :: Software Development :: Build Tools
